odoo/addons/account_asset_management_menu/README.rst
odoo/addons/account_asset_management_menu/__init__.py
odoo/addons/account_asset_management_menu/__manifest__.py
odoo/addons/account_asset_management_menu/i18n/account_asset_management_menu.pot
odoo/addons/account_asset_management_menu/readme/CONFIGURATION.rst
odoo/addons/account_asset_management_menu/readme/CONTRIBUTORS.rst
odoo/addons/account_asset_management_menu/readme/DESCRIPTION.rst
odoo/addons/account_asset_management_menu/static/description/icon.png
odoo/addons/account_asset_management_menu/static/description/index.html
odoo/addons/account_asset_management_menu/views/menuitem.xml
odoo_addon_account_asset_management_menu-15.0.1.0.0.3.dist-info/METADATA
odoo_addon_account_asset_management_menu-15.0.1.0.0.3.dist-info/WHEEL
odoo_addon_account_asset_management_menu-15.0.1.0.0.3.dist-info/top_level.txt
odoo_addon_account_asset_management_menu-15.0.1.0.0.3.dist-info/RECORD
